processamento_imagens_pythonico_DIO/__init__.py
processamento_imagens_pythonico_DIO/processing/__init__.py
processamento_imagens_pythonico_DIO/processing/combination.py
processamento_imagens_pythonico_DIO/processing/transformation.py
processamento_imagens_pythonico_DIO/utils/__init__.py
processamento_imagens_pythonico_DIO/utils/io.py
processamento_imagens_pythonico_DIO/utils/plot.py
processamento_imagens_pythonico_DIO-0.0.1.dist-info/METADATA
processamento_imagens_pythonico_DIO-0.0.1.dist-info/WHEEL
processamento_imagens_pythonico_DIO-0.0.1.dist-info/top_level.txt
processamento_imagens_pythonico_DIO-0.0.1.dist-info/RECORD
