Metadata-Version: 2.1
Name: processamento-imagens-pythonico-DIO
Version: 0.0.1
Summary: Processamento de imagens com Python
Home-page: https://github.com/guilhermercarv/Ciencia-Analise-de-Dados-com-Python
Author: Guilherme
Author-email: guilhermecarvalho056@gmail.com
License: UNKNOWN
Platform: UNKNOWN
Requires-Python: >=3.8
Requires-Dist: matplotlib
Requires-Dist: numpy
Requires-Dist: scikit-image (>=0.16.1)
